<odoo>
    <record id="product_custom_search_view" model="ir.ui.view">
        <field name="model">product.template</field>
        <field name="inherit_id" ref="product.product_template_search_view"/>
        <field name="arch" type="xml">
            <field name="name" position="after">
                <field name="sellers_product_code"/>
            </field>
        </field>
    </record>

    <record id="product_template_only_form_view" model="ir.ui.view">
        <field name="name">product.template.form.inherit</field>
        <field name="model">product.template</field>
        <!-- inherit common view -->
        <field name="inherit_id" ref="product.product_template_form_view"/>
        <field name="arch" type="xml">
            <group name="description">
                <separator string="Internal Description" colspan="4"/>
                <field name="description" colspan="4" nolabel="1" placeholder="This note is for internal use only."/>
            </group>
        </field>
    </record>
</odoo>
